bottender
