Metadata-Version: 1.1
Name: bottender
Version: 0.0.2
Summary: # bottender-py
